.gitignore
LICENSE
README.md
fassst.py
pyproject.toml
riotfile.py
setup.cfg
setup.py
.github/CODEOWNERS
.github/workflows/build_deploy.yml
.github/workflows/ci.yml
fassst.egg-info/PKG-INFO
fassst.egg-info/SOURCES.txt
fassst.egg-info/dependency_links.txt
fassst.egg-info/top_level.txt
src/__init__.py
src/fassst.py
tests/test_fassst.py