Metadata-Version: 2.1
Name: fassst
Version: 0.1
Summary: helps make your python go fast
Home-page: https://github.com/Kyle-Verhoog/fassst
Author: Patrick Gingras <775.pg.12@gmail.com>, Kyle Verhoog <kyle@verhoog.ca>
Author-email: 775.pg.12@gmail.com, kyle@verhoog.ca
License: Apache 2
Platform: UNKNOWN
Classifier: Programming Language :: Python
Classifier: Programming Language :: Python :: 3.8
Classifier: Programming Language :: Python :: 3.9
Requires-Python: >=3.8
